pydre/__init__.py
pydre/core.py
pydre/project.py
pydre/rois.py
pydre/run.py
pydre/filters/R2DFilters.py
pydre/filters/__init__.py
pydre/filters/common.py
pydre/filters/eyetracking.py
pydre/filters/gazeangle.py
pydre/metrics/R2DMetrics.py
pydre/metrics/__init__.py
pydre/metrics/box.py
pydre/metrics/common.py
pydre/metrics/driverdistraction.py
pydre/metrics/gazeanglecutout.py
pydre-25.3.dist-info/METADATA
pydre-25.3.dist-info/WHEEL
pydre-25.3.dist-info/entry_points.txt
pydre-25.3.dist-info/licenses/LICENSE
pydre-25.3.dist-info/RECORD
