Metadata-Version: 2.3
Name: pydre
Version: 25.3
Summary: Driving simulation data processing engine
Project-URL: Documentation, https://osudsl.github.io/pydre/
Project-URL: Repository, https://github.com/OSUDSL/pydre
Author-email: Thomas Kerwin <kerwin.6@osu.edu>
Keywords: driving simulation
Classifier: Development Status :: 6 - Mature
Classifier: Intended Audience :: Science/Research
Classifier: License :: OSI Approved :: Apache Software License
Classifier: Programming Language :: Python :: 3.12
Classifier: Topic :: Scientific/Engineering :: Information Analysis
Requires-Python: >=3.12
Requires-Dist: icecream
Requires-Dist: jenkspy
Requires-Dist: loguru
Requires-Dist: numpy
Requires-Dist: polars
Requires-Dist: scipy
Requires-Dist: tqdm
Provides-Extra: dev
Requires-Dist: black; extra == 'dev'
Requires-Dist: griffe==1.2.0; extra == 'dev'
Requires-Dist: mkdocs-material; extra == 'dev'
Requires-Dist: mkdocs>=1.6.0; extra == 'dev'
Requires-Dist: mkdocstrings[python]; extra == 'dev'
Requires-Dist: mypy; extra == 'dev'
Requires-Dist: ptpython; extra == 'dev'
Requires-Dist: pytest-cov; extra == 'dev'
Requires-Dist: pytest-datafiles; extra == 'dev'
Requires-Dist: pytest-mock; extra == 'dev'
Requires-Dist: pytest>=8.3.2; extra == 'dev'
